holidaycal/__init__.py
holidaycal/calendar.py
holidaycal/easter.py
holidaycal/holiday.py
holidaycal/observance.py
test_holidaycal/__init__.py
test_holidaycal/test_banking_holidays.py
test_holidaycal/test_calendar.py
test_holidaycal/test_easter.py
test_holidaycal/test_holiday.py
test_holidaycal/test_observance.py
holidaycal-0.0.1.dist-info/LICENSE
holidaycal-0.0.1.dist-info/METADATA
holidaycal-0.0.1.dist-info/WHEEL
holidaycal-0.0.1.dist-info/top_level.txt
holidaycal-0.0.1.dist-info/RECORD
