Metadata-Version: 2.1
Name: holidaycal
Version: 0.0.1
Summary: Holiday calendars for financial analysis
Home-page: https://github.com/jordanhitchcock/holidaycal
License: BSD-3-Clause
Platform: UNKNOWN
Classifier: Programming Language :: Python :: 3
Classifier: Topic :: Office/Business :: Financial
Classifier: Topic :: Office/Business :: Financial :: Investment
Classifier: Topic :: Office/Business :: Scheduling
Requires-Python: >=3.6
License-File: LICENSE
Requires-Dist: python-dateutil (>=2.8.2)
